{
  "lastUpdated": "2026-06-15T12:21:58.665Z",
  "platforms": {
    "twitter": {
      "name": "X (Twitter)",
      "icon": "𝕏",
      "items": [
        {
          "rank": 1,
          "title": "#戌神ころね7周年",
          "url": "https://twitter.com/search?q=%23%E6%88%8C%E7%A5%9E%E3%81%93%E3%82%8D%E3%81%AD7%E5%91%A8%E5%B9%B4",
          "hot": "",
          "platform": "twitter"
        },
        {
          "rank": 2,
          "title": "#مونديال_Ingame",
          "url": "https://twitter.com/search?q=%23%D9%85%D9%88%D9%86%D8%AF%D9%8A%D8%A7%D9%84_Ingame",
          "hot": "",
          "platform": "twitter"
        },
        {
          "rank": 3,
          "title": "#NECOMasterBlasterWomen",
          "url": "https://twitter.com/search?q=%23NECOMasterBlasterWomen",
          "hot": "",
          "platform": "twitter"
        },
        {
          "rank": 4,
          "title": "#THEバトルSHOW",
          "url": "https://twitter.com/search?q=%23THE%E3%83%90%E3%83%88%E3%83%ABSHOW",
          "hot": "",
          "platform": "twitter"
        },
        {
          "rank": 5,
          "title": "#InnovationAtJio",
          "url": "https://twitter.com/search?q=%23InnovationAtJio",
          "hot": "",
          "platform": "twitter"
        },
        {
          "rank": 6,
          "title": "スガキヤ",
          "url": "https://twitter.com/search?q=%E3%82%B9%E3%82%AC%E3%82%AD%E3%83%A4",
          "hot": "",
          "platform": "twitter"
        },
        {
          "rank": 7,
          "title": "ルミナス",
          "url": "https://twitter.com/search?q=%E3%83%AB%E3%83%9F%E3%83%8A%E3%82%B9",
          "hot": "",
          "platform": "twitter"
        },
        {
          "rank": 8,
          "title": "LPU Study Grant",
          "url": "https://twitter.com/search?q=LPU%20Study%20Grant",
          "hot": "",
          "platform": "twitter"
        },
        {
          "rank": 9,
          "title": "HAN NEW TODS AMBASSADOR",
          "url": "https://twitter.com/search?q=HAN%20NEW%20TODS%20AMBASSADOR",
          "hot": "",
          "platform": "twitter"
        },
        {
          "rank": 10,
          "title": "AC Milan",
          "url": "https://twitter.com/search?q=AC%20Milan",
          "hot": "",
          "platform": "twitter"
        },
        {
          "rank": 11,
          "title": "アンドロメダ",
          "url": "https://twitter.com/search?q=%E3%82%A2%E3%83%B3%E3%83%89%E3%83%AD%E3%83%A1%E3%83%80",
          "hot": "",
          "platform": "twitter"
        },
        {
          "rank": 12,
          "title": "エレシュキガル",
          "url": "https://twitter.com/search?q=%E3%82%A8%E3%83%AC%E3%82%B7%E3%83%A5%E3%82%AD%E3%82%AC%E3%83%AB",
          "hot": "",
          "platform": "twitter"
        },
        {
          "rank": 13,
          "title": "ルパン・ザ・ファイヤー",
          "url": "https://twitter.com/search?q=%E3%83%AB%E3%83%91%E3%83%B3%E3%83%BB%E3%82%B6%E3%83%BB%E3%83%95%E3%82%A1%E3%82%A4%E3%83%A4%E3%83%BC",
          "hot": "",
          "platform": "twitter"
        },
        {
          "rank": 14,
          "title": "ASHNISHA SOLAR EXPANSION",
          "url": "https://twitter.com/search?q=ASHNISHA%20SOLAR%20EXPANSION",
          "hot": "",
          "platform": "twitter"
        },
        {
          "rank": 15,
          "title": "Topuria",
          "url": "https://twitter.com/search?q=Topuria",
          "hot": "",
          "platform": "twitter"
        },
        {
          "rank": 16,
          "title": "ムルシエラゴ",
          "url": "https://twitter.com/search?q=%E3%83%A0%E3%83%AB%E3%82%B7%E3%82%A8%E3%83%A9%E3%82%B4",
          "hot": "",
          "platform": "twitter"
        },
        {
          "rank": 17,
          "title": "ゾーシモス",
          "url": "https://twitter.com/search?q=%E3%82%BE%E3%83%BC%E3%82%B7%E3%83%A2%E3%82%B9",
          "hot": "",
          "platform": "twitter"
        },
        {
          "rank": 18,
          "title": "ロザリン",
          "url": "https://twitter.com/search?q=%E3%83%AD%E3%82%B6%E3%83%AA%E3%83%B3",
          "hot": "",
          "platform": "twitter"
        },
        {
          "rank": 19,
          "title": "LINE MAN x Teetee Por",
          "url": "https://twitter.com/search?q=LINE%20MAN%20x%20Teetee%20Por",
          "hot": "",
          "platform": "twitter"
        },
        {
          "rank": 20,
          "title": "Amorim",
          "url": "https://twitter.com/search?q=Amorim",
          "hot": "",
          "platform": "twitter"
        },
        {
          "rank": 21,
          "title": "BTTM",
          "url": "https://twitter.com/search?q=BTTM",
          "hot": "",
          "platform": "twitter"
        },
        {
          "rank": 22,
          "title": "職業差別",
          "url": "https://twitter.com/search?q=%E8%81%B7%E6%A5%AD%E5%B7%AE%E5%88%A5",
          "hot": "",
          "platform": "twitter"
        },
        {
          "rank": 23,
          "title": "Ilia",
          "url": "https://twitter.com/search?q=Ilia",
          "hot": "",
          "platform": "twitter"
        },
        {
          "rank": 24,
          "title": "議員辞職",
          "url": "https://twitter.com/search?q=%E8%AD%B0%E5%93%A1%E8%BE%9E%E8%81%B7",
          "hot": "",
          "platform": "twitter"
        },
        {
          "rank": 25,
          "title": "Good Monday",
          "url": "https://twitter.com/search?q=Good%20Monday",
          "hot": "",
          "platform": "twitter"
        },
        {
          "rank": 26,
          "title": "自衛隊員",
          "url": "https://twitter.com/search?q=%E8%87%AA%E8%A1%9B%E9%9A%8A%E5%93%A1",
          "hot": "",
          "platform": "twitter"
        },
        {
          "rank": 27,
          "title": "Digital ID",
          "url": "https://twitter.com/search?q=Digital%20ID",
          "hot": "",
          "platform": "twitter"
        },
        {
          "rank": 28,
          "title": "ミスドコラボ",
          "url": "https://twitter.com/search?q=%E3%83%9F%E3%82%B9%E3%83%89%E3%82%B3%E3%83%A9%E3%83%9C",
          "hot": "",
          "platform": "twitter"
        },
        {
          "rank": 29,
          "title": "フルンティング",
          "url": "https://twitter.com/search?q=%E3%83%95%E3%83%AB%E3%83%B3%E3%83%86%E3%82%A3%E3%83%B3%E3%82%B0",
          "hot": "",
          "platform": "twitter"
        },
        {
          "rank": 30,
          "title": "Gaethje",
          "url": "https://twitter.com/search?q=Gaethje",
          "hot": "",
          "platform": "twitter"
        }
      ]
    },
    "bilibili": {
      "name": "Bilibili",
      "icon": "📺",
      "items": [
        {
          "rank": 1,
          "title": "《原神》动画短片——「最后的遗产」",
          "url": "https://www.bilibili.com/video/BV1nAJK6PEwh",
          "hot": "256万播放",
          "platform": "bilibili"
        },
        {
          "rank": 2,
          "title": "《兔粮是你的谎言》",
          "url": "https://www.bilibili.com/video/BV1dNJL6XELa",
          "hot": "712万播放",
          "platform": "bilibili"
        },
        {
          "rank": 3,
          "title": "墙那边根本就没有厕所！！",
          "url": "https://www.bilibili.com/video/BV1aEE16YECM",
          "hot": "658万播放",
          "platform": "bilibili"
        },
        {
          "rank": 4,
          "title": "路边一块，经过雕刻，包你看了过目不忘！愿你成为自己的太阳，无需借谁的光",
          "url": "https://www.bilibili.com/video/BV1kFE161Evt",
          "hot": "443万播放",
          "platform": "bilibili"
        },
        {
          "rank": 5,
          "title": "新地图解锁！影视飓风的电竞房？",
          "url": "https://www.bilibili.com/video/BV16kEC6MEWL",
          "hot": "273万播放",
          "platform": "bilibili"
        },
        {
          "rank": 6,
          "title": "看一看早餐的质量怎么样#早餐#食品安全",
          "url": "https://www.bilibili.com/video/BV19sJH6NE2H",
          "hot": "409万播放",
          "platform": "bilibili"
        },
        {
          "rank": 7,
          "title": "《少年》-《下一个是谁7》主题曲",
          "url": "https://www.bilibili.com/video/BV1VbJ56EEm6",
          "hot": "102万播放",
          "platform": "bilibili"
        },
        {
          "rank": 8,
          "title": "无法预测！命运的最后抽卡！【水无月菌】",
          "url": "https://www.bilibili.com/video/BV1uHEC6XEEu",
          "hot": "201万播放",
          "platform": "bilibili"
        },
        {
          "rank": 9,
          "title": "《青春期恐龙幻想物语》",
          "url": "https://www.bilibili.com/video/BV1tUEY6WE3t",
          "hot": "296万播放",
          "platform": "bilibili"
        },
        {
          "rank": 10,
          "title": "不是 我咋上高三了",
          "url": "https://www.bilibili.com/video/BV1MrJ56gE5T",
          "hot": "399万播放",
          "platform": "bilibili"
        },
        {
          "rank": 11,
          "title": "峰峦叠嶂间，此城何处寻？",
          "url": "https://www.bilibili.com/video/BV1QNJu6bEts",
          "hot": "239万播放",
          "platform": "bilibili"
        },
        {
          "rank": 12,
          "title": "迈克尔杰克逊的billiejean，斗胆跳一段。",
          "url": "https://www.bilibili.com/video/BV1dmJP6sEgd",
          "hot": "185万播放",
          "platform": "bilibili"
        },
        {
          "rank": 13,
          "title": "美国“杰斐逊州”在哪里？【神奇组织51】",
          "url": "https://www.bilibili.com/video/BV1jCJs6UE9S",
          "hot": "175万播放",
          "platform": "bilibili"
        },
        {
          "rank": 14,
          "title": "我找东西be like",
          "url": "https://www.bilibili.com/video/BV1iyJV6EEao",
          "hot": "185万播放",
          "platform": "bilibili"
        },
        {
          "rank": 15,
          "title": "洗衣机演奏一首《起风了》，以此纪念我的高中生活",
          "url": "https://www.bilibili.com/video/BV1J9EB6xEAB",
          "hot": "293万播放",
          "platform": "bilibili"
        },
        {
          "rank": 16,
          "title": "我们成功了!核电站隐藏好结局-天下无核 测试服",
          "url": "https://www.bilibili.com/video/BV1tLJp6FEoP",
          "hot": "265万播放",
          "platform": "bilibili"
        },
        {
          "rank": 17,
          "title": "⚡烂梗小孩就要这样制裁⚡",
          "url": "https://www.bilibili.com/video/BV1yBE16UENN",
          "hot": "319万播放",
          "platform": "bilibili"
        },
        {
          "rank": 18,
          "title": "新三国up锐评老三国02：没有对比就没有伤害",
          "url": "https://www.bilibili.com/video/BV1rvEr6NEpF",
          "hot": "122万播放",
          "platform": "bilibili"
        },
        {
          "rank": 19,
          "title": "循环歌单|【illusion】|“【静步の小曲】”",
          "url": "https://www.bilibili.com/video/BV17GEi61EZK",
          "hot": "294万播放",
          "platform": "bilibili"
        },
        {
          "rank": 20,
          "title": "0%成功率的吉尼斯挑战（AI给出的结论）！",
          "url": "https://www.bilibili.com/video/BV1S2Ey6sEYs",
          "hot": "115万播放",
          "platform": "bilibili"
        }
      ]
    },
    "instagram": {
      "name": "Instagram",
      "icon": "📷",
      "items": [
        {
          "rank": 1,
          "title": "#love",
          "url": "https://www.instagram.com/explore/tags/love/",
          "hot": "",
          "platform": "instagram"
        },
        {
          "rank": 2,
          "title": "#instagood",
          "url": "https://www.instagram.com/explore/tags/instagood/",
          "hot": "",
          "platform": "instagram"
        },
        {
          "rank": 3,
          "title": "#fashion",
          "url": "https://www.instagram.com/explore/tags/fashion/",
          "hot": "",
          "platform": "instagram"
        },
        {
          "rank": 4,
          "title": "#photooftheday",
          "url": "https://www.instagram.com/explore/tags/photooftheday/",
          "hot": "",
          "platform": "instagram"
        },
        {
          "rank": 5,
          "title": "#photography",
          "url": "https://www.instagram.com/explore/tags/photography/",
          "hot": "",
          "platform": "instagram"
        },
        {
          "rank": 6,
          "title": "#beautiful",
          "url": "https://www.instagram.com/explore/tags/beautiful/",
          "hot": "",
          "platform": "instagram"
        },
        {
          "rank": 7,
          "title": "#art",
          "url": "https://www.instagram.com/explore/tags/art/",
          "hot": "",
          "platform": "instagram"
        },
        {
          "rank": 8,
          "title": "#picoftheday",
          "url": "https://www.instagram.com/explore/tags/picoftheday/",
          "hot": "",
          "platform": "instagram"
        },
        {
          "rank": 9,
          "title": "#nature",
          "url": "https://www.instagram.com/explore/tags/nature/",
          "hot": "",
          "platform": "instagram"
        },
        {
          "rank": 10,
          "title": "#happy",
          "url": "https://www.instagram.com/explore/tags/happy/",
          "hot": "",
          "platform": "instagram"
        },
        {
          "rank": 11,
          "title": "#follow",
          "url": "https://www.instagram.com/explore/tags/follow/",
          "hot": "",
          "platform": "instagram"
        },
        {
          "rank": 12,
          "title": "#travel",
          "url": "https://www.instagram.com/explore/tags/travel/",
          "hot": "",
          "platform": "instagram"
        },
        {
          "rank": 13,
          "title": "#style",
          "url": "https://www.instagram.com/explore/tags/style/",
          "hot": "",
          "platform": "instagram"
        },
        {
          "rank": 14,
          "title": "#instadaily",
          "url": "https://www.instagram.com/explore/tags/instadaily/",
          "hot": "",
          "platform": "instagram"
        },
        {
          "rank": 15,
          "title": "#reels",
          "url": "https://www.instagram.com/explore/tags/reels/",
          "hot": "",
          "platform": "instagram"
        },
        {
          "rank": 16,
          "title": "#like",
          "url": "https://www.instagram.com/explore/tags/like/",
          "hot": "",
          "platform": "instagram"
        },
        {
          "rank": 17,
          "title": "#fitness",
          "url": "https://www.instagram.com/explore/tags/fitness/",
          "hot": "",
          "platform": "instagram"
        },
        {
          "rank": 18,
          "title": "#life",
          "url": "https://www.instagram.com/explore/tags/life/",
          "hot": "",
          "platform": "instagram"
        },
        {
          "rank": 19,
          "title": "#beauty",
          "url": "https://www.instagram.com/explore/tags/beauty/",
          "hot": "",
          "platform": "instagram"
        },
        {
          "rank": 20,
          "title": "#food",
          "url": "https://www.instagram.com/explore/tags/food/",
          "hot": "",
          "platform": "instagram"
        }
      ]
    },
    "zhihu": {
      "name": "知乎",
      "icon": "💡",
      "items": []
    },
    "baidu": {
      "name": "百度热搜",
      "icon": "🔍",
      "items": [
        {
          "rank": 1,
          "title": "我将无我 不负人民",
          "url": "https://www.baidu.com/s?wd=%E6%88%91%E5%B0%86%E6%97%A0%E6%88%91%20%E4%B8%8D%E8%B4%9F%E4%BA%BA%E6%B0%91",
          "hot": "",
          "platform": "baidu"
        },
        {
          "rank": 2,
          "title": "山姆向会员致歉",
          "url": "https://www.baidu.com/s?wd=%E5%B1%B1%E5%A7%86%E5%90%91%E4%BC%9A%E5%91%98%E8%87%B4%E6%AD%89",
          "hot": "",
          "platform": "baidu"
        },
        {
          "rank": 3,
          "title": "3280元眼镜进货价仅126元",
          "url": "https://www.baidu.com/s?wd=3280%E5%85%83%E7%9C%BC%E9%95%9C%E8%BF%9B%E8%B4%A7%E4%BB%B7%E4%BB%85126%E5%85%83",
          "hot": "",
          "platform": "baidu"
        },
        {
          "rank": 4,
          "title": "中国“纯硅”成功突破",
          "url": "https://www.baidu.com/s?wd=%E4%B8%AD%E5%9B%BD%E2%80%9C%E7%BA%AF%E7%A1%85%E2%80%9D%E6%88%90%E5%8A%9F%E7%AA%81%E7%A0%B4",
          "hot": "",
          "platform": "baidu"
        },
        {
          "rank": 5,
          "title": "不懂球的商家 卖出了40万个足球",
          "url": "https://www.baidu.com/s?wd=%E4%B8%8D%E6%87%82%E7%90%83%E7%9A%84%E5%95%86%E5%AE%B6%20%E5%8D%96%E5%87%BA%E4%BA%8640%E4%B8%87%E4%B8%AA%E8%B6%B3%E7%90%83",
          "hot": "",
          "platform": "baidu"
        },
        {
          "rank": 6,
          "title": "大暴雨、特大暴雨！多预警齐发",
          "url": "https://www.baidu.com/s?wd=%E5%A4%A7%E6%9A%B4%E9%9B%A8%E3%80%81%E7%89%B9%E5%A4%A7%E6%9A%B4%E9%9B%A8%EF%BC%81%E5%A4%9A%E9%A2%84%E8%AD%A6%E9%BD%90%E5%8F%91",
          "hot": "",
          "platform": "baidu"
        },
        {
          "rank": 7,
          "title": "网民编造涉食品安全谣言被拘",
          "url": "https://www.baidu.com/s?wd=%E7%BD%91%E6%B0%91%E7%BC%96%E9%80%A0%E6%B6%89%E9%A3%9F%E5%93%81%E5%AE%89%E5%85%A8%E8%B0%A3%E8%A8%80%E8%A2%AB%E6%8B%98",
          "hot": "",
          "platform": "baidu"
        },
        {
          "rank": 8,
          "title": "世界杯史上最小参赛国主教练哭了",
          "url": "https://www.baidu.com/s?wd=%E4%B8%96%E7%95%8C%E6%9D%AF%E5%8F%B2%E4%B8%8A%E6%9C%80%E5%B0%8F%E5%8F%82%E8%B5%9B%E5%9B%BD%E4%B8%BB%E6%95%99%E7%BB%83%E5%93%AD%E4%BA%86",
          "hot": "",
          "platform": "baidu"
        },
        {
          "rank": 9,
          "title": "鱼缸“哐”一声爆裂 损失30多万",
          "url": "https://www.baidu.com/s?wd=%E9%B1%BC%E7%BC%B8%E2%80%9C%E5%93%90%E2%80%9D%E4%B8%80%E5%A3%B0%E7%88%86%E8%A3%82%20%E6%8D%9F%E5%A4%B130%E5%A4%9A%E4%B8%87",
          "hot": "",
          "platform": "baidu"
        },
        {
          "rank": 10,
          "title": "“银行追债不能把人逼上绝路”",
          "url": "https://www.baidu.com/s?wd=%E2%80%9C%E9%93%B6%E8%A1%8C%E8%BF%BD%E5%80%BA%E4%B8%8D%E8%83%BD%E6%8A%8A%E4%BA%BA%E9%80%BC%E4%B8%8A%E7%BB%9D%E8%B7%AF%E2%80%9D",
          "hot": "",
          "platform": "baidu"
        },
        {
          "rank": 11,
          "title": "人民日报评“用智能眼镜偷拍空姐”",
          "url": "https://www.baidu.com/s?wd=%E4%BA%BA%E6%B0%91%E6%97%A5%E6%8A%A5%E8%AF%84%E2%80%9C%E7%94%A8%E6%99%BA%E8%83%BD%E7%9C%BC%E9%95%9C%E5%81%B7%E6%8B%8D%E7%A9%BA%E5%A7%90%E2%80%9D",
          "hot": "",
          "platform": "baidu"
        },
        {
          "rank": 12,
          "title": "博主编造涉货车司机与货主谣言被罚",
          "url": "https://www.baidu.com/s?wd=%E5%8D%9A%E4%B8%BB%E7%BC%96%E9%80%A0%E6%B6%89%E8%B4%A7%E8%BD%A6%E5%8F%B8%E6%9C%BA%E4%B8%8E%E8%B4%A7%E4%B8%BB%E8%B0%A3%E8%A8%80%E8%A2%AB%E7%BD%9A",
          "hot": "",
          "platform": "baidu"
        },
        {
          "rank": 13,
          "title": "渝见小面老板称无法坦然接受道歉",
          "url": "https://www.baidu.com/s?wd=%E6%B8%9D%E8%A7%81%E5%B0%8F%E9%9D%A2%E8%80%81%E6%9D%BF%E7%A7%B0%E6%97%A0%E6%B3%95%E5%9D%A6%E7%84%B6%E6%8E%A5%E5%8F%97%E9%81%93%E6%AD%89",
          "hot": "",
          "platform": "baidu"
        },
        {
          "rank": 14,
          "title": "女子驾宝马车冲撞丧事现场 当地通报",
          "url": "https://www.baidu.com/s?wd=%E5%A5%B3%E5%AD%90%E9%A9%BE%E5%AE%9D%E9%A9%AC%E8%BD%A6%E5%86%B2%E6%92%9E%E4%B8%A7%E4%BA%8B%E7%8E%B0%E5%9C%BA%20%E5%BD%93%E5%9C%B0%E9%80%9A%E6%8A%A5",
          "hot": "",
          "platform": "baidu"
        },
        {
          "rank": 15,
          "title": "小龙虾竟然还能这么用",
          "url": "https://www.baidu.com/s?wd=%E5%B0%8F%E9%BE%99%E8%99%BE%E7%AB%9F%E7%84%B6%E8%BF%98%E8%83%BD%E8%BF%99%E4%B9%88%E7%94%A8",
          "hot": "",
          "platform": "baidu"
        },
        {
          "rank": 16,
          "title": "你买的粽子安全吗？官方抽检出炉",
          "url": "https://www.baidu.com/s?wd=%E4%BD%A0%E4%B9%B0%E7%9A%84%E7%B2%BD%E5%AD%90%E5%AE%89%E5%85%A8%E5%90%97%EF%BC%9F%E5%AE%98%E6%96%B9%E6%8A%BD%E6%A3%80%E5%87%BA%E7%82%89",
          "hot": "",
          "platform": "baidu"
        },
        {
          "rank": 17,
          "title": "中方回应“美伊达成协议”",
          "url": "https://www.baidu.com/s?wd=%E4%B8%AD%E6%96%B9%E5%9B%9E%E5%BA%94%E2%80%9C%E7%BE%8E%E4%BC%8A%E8%BE%BE%E6%88%90%E5%8D%8F%E8%AE%AE%E2%80%9D",
          "hot": "",
          "platform": "baidu"
        },
        {
          "rank": 18,
          "title": "苏翊鸣回应恋情传闻",
          "url": "https://www.baidu.com/s?wd=%E8%8B%8F%E7%BF%8A%E9%B8%A3%E5%9B%9E%E5%BA%94%E6%81%8B%E6%83%85%E4%BC%A0%E9%97%BB",
          "hot": "",
          "platform": "baidu"
        },
        {
          "rank": 19,
          "title": "伊朗队花5小时抵美 飞机试2次才落地",
          "url": "https://www.baidu.com/s?wd=%E4%BC%8A%E6%9C%97%E9%98%9F%E8%8A%B15%E5%B0%8F%E6%97%B6%E6%8A%B5%E7%BE%8E%20%E9%A3%9E%E6%9C%BA%E8%AF%952%E6%AC%A1%E6%89%8D%E8%90%BD%E5%9C%B0",
          "hot": "",
          "platform": "baidu"
        },
        {
          "rank": 20,
          "title": "网友整理明星真名及艺名名单",
          "url": "https://www.baidu.com/s?wd=%E7%BD%91%E5%8F%8B%E6%95%B4%E7%90%86%E6%98%8E%E6%98%9F%E7%9C%9F%E5%90%8D%E5%8F%8A%E8%89%BA%E5%90%8D%E5%90%8D%E5%8D%95",
          "hot": "",
          "platform": "baidu"
        },
        {
          "rank": 21,
          "title": "德国队颜值断崖式下滑",
          "url": "https://www.baidu.com/s?wd=%E5%BE%B7%E5%9B%BD%E9%98%9F%E9%A2%9C%E5%80%BC%E6%96%AD%E5%B4%96%E5%BC%8F%E4%B8%8B%E6%BB%91",
          "hot": "",
          "platform": "baidu"
        },
        {
          "rank": 22,
          "title": "英国官宣16岁以下社交媒体禁令",
          "url": "https://www.baidu.com/s?wd=%E8%8B%B1%E5%9B%BD%E5%AE%98%E5%AE%A316%E5%B2%81%E4%BB%A5%E4%B8%8B%E7%A4%BE%E4%BA%A4%E5%AA%92%E4%BD%93%E7%A6%81%E4%BB%A4",
          "hot": "",
          "platform": "baidu"
        },
        {
          "rank": 23,
          "title": "长沙酒店房间现“充气娃娃”租借柜",
          "url": "https://www.baidu.com/s?wd=%E9%95%BF%E6%B2%99%E9%85%92%E5%BA%97%E6%88%BF%E9%97%B4%E7%8E%B0%E2%80%9C%E5%85%85%E6%B0%94%E5%A8%83%E5%A8%83%E2%80%9D%E7%A7%9F%E5%80%9F%E6%9F%9C",
          "hot": "",
          "platform": "baidu"
        },
        {
          "rank": 24,
          "title": "“包公”也去看世界杯了",
          "url": "https://www.baidu.com/s?wd=%E2%80%9C%E5%8C%85%E5%85%AC%E2%80%9D%E4%B9%9F%E5%8E%BB%E7%9C%8B%E4%B8%96%E7%95%8C%E6%9D%AF%E4%BA%86",
          "hot": "",
          "platform": "baidu"
        },
        {
          "rank": 25,
          "title": "世界杯球队巡礼：西班牙队",
          "url": "https://www.baidu.com/s?wd=%E4%B8%96%E7%95%8C%E6%9D%AF%E7%90%83%E9%98%9F%E5%B7%A1%E7%A4%BC%EF%BC%9A%E8%A5%BF%E7%8F%AD%E7%89%99%E9%98%9F",
          "hot": "",
          "platform": "baidu"
        },
        {
          "rank": 26,
          "title": "詹俊预测西班牙“首秀”：大胜有难度",
          "url": "https://www.baidu.com/s?wd=%E8%A9%B9%E4%BF%8A%E9%A2%84%E6%B5%8B%E8%A5%BF%E7%8F%AD%E7%89%99%E2%80%9C%E9%A6%96%E7%A7%80%E2%80%9D%EF%BC%9A%E5%A4%A7%E8%83%9C%E6%9C%89%E9%9A%BE%E5%BA%A6",
          "hot": "",
          "platform": "baidu"
        },
        {
          "rank": 27,
          "title": "多方回应13岁学生被误诊艾滋病",
          "url": "https://www.baidu.com/s?wd=%E5%A4%9A%E6%96%B9%E5%9B%9E%E5%BA%9413%E5%B2%81%E5%AD%A6%E7%94%9F%E8%A2%AB%E8%AF%AF%E8%AF%8A%E8%89%BE%E6%BB%8B%E7%97%85",
          "hot": "",
          "platform": "baidu"
        },
        {
          "rank": 28,
          "title": "梅西看德国队比赛玩嗨了",
          "url": "https://www.baidu.com/s?wd=%E6%A2%85%E8%A5%BF%E7%9C%8B%E5%BE%B7%E5%9B%BD%E9%98%9F%E6%AF%94%E8%B5%9B%E7%8E%A9%E5%97%A8%E4%BA%86",
          "hot": "",
          "platform": "baidu"
        },
        {
          "rank": 29,
          "title": "溜溜梅上市首日暴涨超190%",
          "url": "https://www.baidu.com/s?wd=%E6%BA%9C%E6%BA%9C%E6%A2%85%E4%B8%8A%E5%B8%82%E9%A6%96%E6%97%A5%E6%9A%B4%E6%B6%A8%E8%B6%85190%25",
          "hot": "",
          "platform": "baidu"
        },
        {
          "rank": 30,
          "title": "暴雨橙色预警！10余省份大到暴雨",
          "url": "https://www.baidu.com/s?wd=%E6%9A%B4%E9%9B%A8%E6%A9%99%E8%89%B2%E9%A2%84%E8%AD%A6%EF%BC%8110%E4%BD%99%E7%9C%81%E4%BB%BD%E5%A4%A7%E5%88%B0%E6%9A%B4%E9%9B%A8",
          "hot": "",
          "platform": "baidu"
        }
      ]
    },
    "toutiao": {
      "name": "今日头条",
      "icon": "📰",
      "items": [
        {
          "rank": 1,
          "title": "3280元眼镜进货价仅126元",
          "url": "https://www.toutiao.com/trending/7651086991836626985/?category_name=topic_innerflow&event_type=hot_board&log_pb=%7B%22category_name%22%3A%22topic_innerflow%22%2C%22cluster_type%22%3A%228%22%2C%22enter_from%22%3A%22click_category%22%2C%22entrance_hotspot%22%3A%22outside%22%2C%22event_type%22%3A%22hot_board%22%2C%22hot_board_cluster_id%22%3A%227651086991836626985%22%2C%22hot_board_impr_id%22%3A%2220260615202157ABC07E8618FDA919B432%22%2C%22jump_page%22%3A%22hot_board_page%22%2C%22location%22%3A%22news_hot_card%22%2C%22page_location%22%3A%22hot_board_page%22%2C%22source%22%3A%22trending_tab%22%2C%22style_id%22%3A%2240132%22%2C%22title%22%3A%223280%E5%85%83%E7%9C%BC%E9%95%9C%E8%BF%9B%E8%B4%A7%E4%BB%B7%E4%BB%85126%E5%85%83%22%7D&rank=&style_id=40132&topic_id=7651086991836626985",
          "hot": "2199万",
          "platform": "toutiao"
        },
        {
          "rank": 2,
          "title": "诺奖得主炮轰马斯克是真人版庞氏骗局",
          "url": "https://www.toutiao.com/trending/7650456833015676978/?category_name=topic_innerflow&event_type=hot_board&log_pb=%7B%22category_name%22%3A%22topic_innerflow%22%2C%22cluster_type%22%3A%2212%22%2C%22enter_from%22%3A%22click_category%22%2C%22entrance_hotspot%22%3A%22outside%22%2C%22event_type%22%3A%22hot_board%22%2C%22hot_board_cluster_id%22%3A%227650456833015676978%22%2C%22hot_board_impr_id%22%3A%2220260615202157ABC07E8618FDA919B432%22%2C%22jump_page%22%3A%22hot_board_page%22%2C%22location%22%3A%22news_hot_card%22%2C%22page_location%22%3A%22hot_board_page%22%2C%22source%22%3A%22trending_tab%22%2C%22style_id%22%3A%2240132%22%2C%22title%22%3A%22%E8%AF%BA%E5%A5%96%E5%BE%97%E4%B8%BB%E7%82%AE%E8%BD%B0%E9%A9%AC%E6%96%AF%E5%85%8B%E6%98%AF%E7%9C%9F%E4%BA%BA%E7%89%88%E5%BA%9E%E6%B0%8F%E9%AA%97%E5%B1%80%22%7D&rank=&style_id=40132&topic_id=7650456833015676978",
          "hot": "1989万",
          "platform": "toutiao"
        },
        {
          "rank": 3,
          "title": "纳入国家顶层部署的“六张网”",
          "url": "https://www.toutiao.com/article/7651450906898121250",
          "hot": "1800万",
          "platform": "toutiao"
        },
        {
          "rank": 4,
          "title": "小电驴三蹦子全球爆单",
          "url": "https://www.toutiao.com/trending/7651547737498075145/?category_name=topic_innerflow&event_type=hot_board&log_pb=%7B%22category_name%22%3A%22topic_innerflow%22%2C%22cluster_type%22%3A%220%22%2C%22enter_from%22%3A%22click_category%22%2C%22entrance_hotspot%22%3A%22outside%22%2C%22event_type%22%3A%22hot_board%22%2C%22hot_board_cluster_id%22%3A%227651547737498075145%22%2C%22hot_board_impr_id%22%3A%2220260615202157ABC07E8618FDA919B432%22%2C%22jump_page%22%3A%22hot_board_page%22%2C%22location%22%3A%22news_hot_card%22%2C%22page_location%22%3A%22hot_board_page%22%2C%22source%22%3A%22trending_tab%22%2C%22style_id%22%3A%2240132%22%2C%22title%22%3A%22%E5%B0%8F%E7%94%B5%E9%A9%B4%E4%B8%89%E8%B9%A6%E5%AD%90%E5%85%A8%E7%90%83%E7%88%86%E5%8D%95%22%7D&rank=&style_id=40132&topic_id=7651547737498075145",
          "hot": "1629万",
          "platform": "toutiao"
        },
        {
          "rank": 5,
          "title": "世界杯史上最小参赛国主教练哭了",
          "url": "https://www.toutiao.com/trending/7650494256829743110/?category_name=topic_innerflow&event_type=hot_board&log_pb=%7B%22category_name%22%3A%22topic_innerflow%22%2C%22cluster_type%22%3A%222%22%2C%22enter_from%22%3A%22click_category%22%2C%22entrance_hotspot%22%3A%22outside%22%2C%22event_type%22%3A%22hot_board%22%2C%22hot_board_cluster_id%22%3A%227650494256829743110%22%2C%22hot_board_impr_id%22%3A%2220260615202157ABC07E8618FDA919B432%22%2C%22jump_page%22%3A%22hot_board_page%22%2C%22location%22%3A%22news_hot_card%22%2C%22page_location%22%3A%22hot_board_page%22%2C%22source%22%3A%22trending_tab%22%2C%22style_id%22%3A%2240132%22%2C%22title%22%3A%22%E4%B8%96%E7%95%8C%E6%9D%AF%E5%8F%B2%E4%B8%8A%E6%9C%80%E5%B0%8F%E5%8F%82%E8%B5%9B%E5%9B%BD%E4%B8%BB%E6%95%99%E7%BB%83%E5%93%AD%E4%BA%86%22%7D&rank=&style_id=40132&topic_id=7650494256829743110",
          "hot": "1474万",
          "platform": "toutiao"
        },
        {
          "rank": 6,
          "title": "净网：马某编造食品安全谣言被拘留",
          "url": "https://www.toutiao.com/trending/7650423542397403172/?category_name=topic_innerflow&event_type=hot_board&log_pb=%7B%22category_name%22%3A%22topic_innerflow%22%2C%22cluster_type%22%3A%222%22%2C%22enter_from%22%3A%22click_category%22%2C%22entrance_hotspot%22%3A%22outside%22%2C%22event_type%22%3A%22hot_board%22%2C%22hot_board_cluster_id%22%3A%227650423542397403172%22%2C%22hot_board_impr_id%22%3A%2220260615202157ABC07E8618FDA919B432%22%2C%22jump_page%22%3A%22hot_board_page%22%2C%22location%22%3A%22news_hot_card%22%2C%22page_location%22%3A%22hot_board_page%22%2C%22source%22%3A%22trending_tab%22%2C%22style_id%22%3A%2240132%22%2C%22title%22%3A%22%E5%87%80%E7%BD%91%EF%BC%9A%E9%A9%AC%E6%9F%90%E7%BC%96%E9%80%A0%E9%A3%9F%E5%93%81%E5%AE%89%E5%85%A8%E8%B0%A3%E8%A8%80%E8%A2%AB%E6%8B%98%E7%95%99%22%7D&rank=&style_id=40132&topic_id=7650423542397403172",
          "hot": "1333万",
          "platform": "toutiao"
        },
        {
          "rank": 7,
          "title": "官方通报女子驾宝马撞丧事现场",
          "url": "https://www.toutiao.com/trending/7651552085439447094/?category_name=topic_innerflow&event_type=hot_board&log_pb=%7B%22category_name%22%3A%22topic_innerflow%22%2C%22cluster_type%22%3A%220%22%2C%22enter_from%22%3A%22click_category%22%2C%22entrance_hotspot%22%3A%22outside%22%2C%22event_type%22%3A%22hot_board%22%2C%22hot_board_cluster_id%22%3A%227651552085439447094%22%2C%22hot_board_impr_id%22%3A%2220260615202157ABC07E8618FDA919B432%22%2C%22jump_page%22%3A%22hot_board_page%22%2C%22location%22%3A%22news_hot_card%22%2C%22page_location%22%3A%22hot_board_page%22%2C%22source%22%3A%22trending_tab%22%2C%22style_id%22%3A%2240132%22%2C%22title%22%3A%22%E5%AE%98%E6%96%B9%E9%80%9A%E6%8A%A5%E5%A5%B3%E5%AD%90%E9%A9%BE%E5%AE%9D%E9%A9%AC%E6%92%9E%E4%B8%A7%E4%BA%8B%E7%8E%B0%E5%9C%BA%22%7D&rank=&style_id=40132&topic_id=7651552085439447094",
          "hot": "1206万",
          "platform": "toutiao"
        },
        {
          "rank": 8,
          "title": "农户夜间抢收麦子场面震撼",
          "url": "https://www.toutiao.com/trending/7650844868349722633/?category_name=topic_innerflow&event_type=hot_board&log_pb=%7B%22category_name%22%3A%22topic_innerflow%22%2C%22cluster_type%22%3A%226%22%2C%22enter_from%22%3A%22click_category%22%2C%22entrance_hotspot%22%3A%22outside%22%2C%22event_type%22%3A%22hot_board%22%2C%22hot_board_cluster_id%22%3A%227650844868349722633%22%2C%22hot_board_impr_id%22%3A%2220260615202157ABC07E8618FDA919B432%22%2C%22jump_page%22%3A%22hot_board_page%22%2C%22location%22%3A%22news_hot_card%22%2C%22page_location%22%3A%22hot_board_page%22%2C%22source%22%3A%22trending_tab%22%2C%22style_id%22%3A%2240132%22%2C%22title%22%3A%22%E5%86%9C%E6%88%B7%E5%A4%9C%E9%97%B4%E6%8A%A2%E6%94%B6%E9%BA%A6%E5%AD%90%E5%9C%BA%E9%9D%A2%E9%9C%87%E6%92%BC%22%7D&rank=&style_id=40132&topic_id=7650844868349722633",
          "hot": "1092万",
          "platform": "toutiao"
        },
        {
          "rank": 9,
          "title": "主持人：C罗正毁掉葡萄牙夺世界杯机会",
          "url": "https://www.toutiao.com/trending/7650331910644842542/?category_name=topic_innerflow&event_type=hot_board&log_pb=%7B%22category_name%22%3A%22topic_innerflow%22%2C%22cluster_type%22%3A%2212%22%2C%22enter_from%22%3A%22click_category%22%2C%22entrance_hotspot%22%3A%22outside%22%2C%22event_type%22%3A%22hot_board%22%2C%22hot_board_cluster_id%22%3A%227650331910644842542%22%2C%22hot_board_impr_id%22%3A%2220260615202157ABC07E8618FDA919B432%22%2C%22jump_page%22%3A%22hot_board_page%22%2C%22location%22%3A%22news_hot_card%22%2C%22page_location%22%3A%22hot_board_page%22%2C%22source%22%3A%22trending_tab%22%2C%22style_id%22%3A%2240132%22%2C%22title%22%3A%22%E4%B8%BB%E6%8C%81%E4%BA%BA%EF%BC%9AC%E7%BD%97%E6%AD%A3%E6%AF%81%E6%8E%89%E8%91%A1%E8%90%84%E7%89%99%E5%A4%BA%E4%B8%96%E7%95%8C%E6%9D%AF%E6%9C%BA%E4%BC%9A%22%7D&rank=&style_id=40132&topic_id=7650331910644842542",
          "hot": "988万",
          "platform": "toutiao"
        },
        {
          "rank": 10,
          "title": "学生把校领导寄语写进高考作文",
          "url": "https://www.toutiao.com/trending/7651119937982185515/?category_name=topic_innerflow&event_type=hot_board&log_pb=%7B%22category_name%22%3A%22topic_innerflow%22%2C%22cluster_type%22%3A%228%22%2C%22enter_from%22%3A%22click_category%22%2C%22entrance_hotspot%22%3A%22outside%22%2C%22event_type%22%3A%22hot_board%22%2C%22hot_board_cluster_id%22%3A%227651119937982185515%22%2C%22hot_board_impr_id%22%3A%2220260615202157ABC07E8618FDA919B432%22%2C%22jump_page%22%3A%22hot_board_page%22%2C%22location%22%3A%22news_hot_card%22%2C%22page_location%22%3A%22hot_board_page%22%2C%22source%22%3A%22trending_tab%22%2C%22style_id%22%3A%2240132%22%2C%22title%22%3A%22%E5%AD%A6%E7%94%9F%E6%8A%8A%E6%A0%A1%E9%A2%86%E5%AF%BC%E5%AF%84%E8%AF%AD%E5%86%99%E8%BF%9B%E9%AB%98%E8%80%83%E4%BD%9C%E6%96%87%22%7D&rank=&style_id=40132&topic_id=7651119937982185515",
          "hot": "894万",
          "platform": "toutiao"
        },
        {
          "rank": 11,
          "title": "伊朗队亮相洛杉矶体育场",
          "url": "https://www.toutiao.com/trending/7651497616207413299/?category_name=topic_innerflow&event_type=hot_board&log_pb=%7B%22category_name%22%3A%22topic_innerflow%22%2C%22cluster_type%22%3A%222%22%2C%22enter_from%22%3A%22click_category%22%2C%22entrance_hotspot%22%3A%22outside%22%2C%22event_type%22%3A%22hot_board%22%2C%22hot_board_cluster_id%22%3A%227651497616207413299%22%2C%22hot_board_impr_id%22%3A%2220260615202157ABC07E8618FDA919B432%22%2C%22jump_page%22%3A%22hot_board_page%22%2C%22location%22%3A%22news_hot_card%22%2C%22page_location%22%3A%22hot_board_page%22%2C%22source%22%3A%22trending_tab%22%2C%22style_id%22%3A%2240132%22%2C%22title%22%3A%22%E4%BC%8A%E6%9C%97%E9%98%9F%E4%BA%AE%E7%9B%B8%E6%B4%9B%E6%9D%89%E7%9F%B6%E4%BD%93%E8%82%B2%E5%9C%BA%22%7D&rank=&style_id=40132&topic_id=7651497616207413299",
          "hot": "809万",
          "platform": "toutiao"
        },
        {
          "rank": 12,
          "title": "网传南通“桥掉下来了”系谣言",
          "url": "https://www.toutiao.com/trending/7650465919038619689/?category_name=topic_innerflow&event_type=hot_board&log_pb=%7B%22category_name%22%3A%22topic_innerflow%22%2C%22cluster_type%22%3A%226%22%2C%22enter_from%22%3A%22click_category%22%2C%22entrance_hotspot%22%3A%22outside%22%2C%22event_type%22%3A%22hot_board%22%2C%22hot_board_cluster_id%22%3A%227650465919038619689%22%2C%22hot_board_impr_id%22%3A%2220260615202157ABC07E8618FDA919B432%22%2C%22jump_page%22%3A%22hot_board_page%22%2C%22location%22%3A%22news_hot_card%22%2C%22page_location%22%3A%22hot_board_page%22%2C%22source%22%3A%22trending_tab%22%2C%22style_id%22%3A%2240132%22%2C%22title%22%3A%22%E7%BD%91%E4%BC%A0%E5%8D%97%E9%80%9A%E2%80%9C%E6%A1%A5%E6%8E%89%E4%B8%8B%E6%9D%A5%E4%BA%86%E2%80%9D%E7%B3%BB%E8%B0%A3%E8%A8%80%22%7D&rank=&style_id=40132&topic_id=7650465919038619689",
          "hot": "732万",
          "platform": "toutiao"
        },
        {
          "rank": 13,
          "title": "印度男子骚扰女大学生被警方打脚心",
          "url": "https://www.toutiao.com/trending/7651557590384230410/?category_name=topic_innerflow&event_type=hot_board&log_pb=%7B%22category_name%22%3A%22topic_innerflow%22%2C%22cluster_type%22%3A%226%22%2C%22enter_from%22%3A%22click_category%22%2C%22entrance_hotspot%22%3A%22outside%22%2C%22event_type%22%3A%22hot_board%22%2C%22hot_board_cluster_id%22%3A%227651557590384230410%22%2C%22hot_board_impr_id%22%3A%2220260615202157ABC07E8618FDA919B432%22%2C%22jump_page%22%3A%22hot_board_page%22%2C%22location%22%3A%22news_hot_card%22%2C%22page_location%22%3A%22hot_board_page%22%2C%22source%22%3A%22trending_tab%22%2C%22style_id%22%3A%2240132%22%2C%22title%22%3A%22%E5%8D%B0%E5%BA%A6%E7%94%B7%E5%AD%90%E9%AA%9A%E6%89%B0%E5%A5%B3%E5%A4%A7%E5%AD%A6%E7%94%9F%E8%A2%AB%E8%AD%A6%E6%96%B9%E6%89%93%E8%84%9A%E5%BF%83%22%7D&rank=&style_id=40132&topic_id=7651557590384230410",
          "hot": "662万",
          "platform": "toutiao"
        },
        {
          "rank": 14,
          "title": "中方回应美伊达成和平协议",
          "url": "https://www.toutiao.com/trending/7651131985116614185/?category_name=topic_innerflow&event_type=hot_board&log_pb=%7B%22category_name%22%3A%22topic_innerflow%22%2C%22cluster_type%22%3A%222%22%2C%22enter_from%22%3A%22click_category%22%2C%22entrance_hotspot%22%3A%22outside%22%2C%22event_type%22%3A%22hot_board%22%2C%22hot_board_cluster_id%22%3A%227651131985116614185%22%2C%22hot_board_impr_id%22%3A%2220260615202157ABC07E8618FDA919B432%22%2C%22jump_page%22%3A%22hot_board_page%22%2C%22location%22%3A%22news_hot_card%22%2C%22page_location%22%3A%22hot_board_page%22%2C%22source%22%3A%22trending_tab%22%2C%22style_id%22%3A%2240132%22%2C%22title%22%3A%22%E4%B8%AD%E6%96%B9%E5%9B%9E%E5%BA%94%E7%BE%8E%E4%BC%8A%E8%BE%BE%E6%88%90%E5%92%8C%E5%B9%B3%E5%8D%8F%E8%AE%AE%22%7D&rank=&style_id=40132&topic_id=7651131985116614185",
          "hot": "599万",
          "platform": "toutiao"
        },
        {
          "rank": 15,
          "title": "俄对乌发动大规模打击",
          "url": "https://www.toutiao.com/trending/7651558133848637483/?category_name=topic_innerflow&event_type=hot_board&log_pb=%7B%22category_name%22%3A%22topic_innerflow%22%2C%22cluster_type%22%3A%220%22%2C%22enter_from%22%3A%22click_category%22%2C%22entrance_hotspot%22%3A%22outside%22%2C%22event_type%22%3A%22hot_board%22%2C%22hot_board_cluster_id%22%3A%227651558133848637483%22%2C%22hot_board_impr_id%22%3A%2220260615202157ABC07E8618FDA919B432%22%2C%22jump_page%22%3A%22hot_board_page%22%2C%22location%22%3A%22news_hot_card%22%2C%22page_location%22%3A%22hot_board_page%22%2C%22source%22%3A%22trending_tab%22%2C%22style_id%22%3A%2240132%22%2C%22title%22%3A%22%E4%BF%84%E5%AF%B9%E4%B9%8C%E5%8F%91%E5%8A%A8%E5%A4%A7%E8%A7%84%E6%A8%A1%E6%89%93%E5%87%BB%22%7D&rank=&style_id=40132&topic_id=7651558133848637483",
          "hot": "542万",
          "platform": "toutiao"
        },
        {
          "rank": 16,
          "title": "3亿北斗工程现“脆皮底座”",
          "url": "https://www.toutiao.com/trending/7651272977132109833/?category_name=topic_innerflow&event_type=hot_board&log_pb=%7B%22category_name%22%3A%22topic_innerflow%22%2C%22cluster_type%22%3A%221%22%2C%22enter_from%22%3A%22click_category%22%2C%22entrance_hotspot%22%3A%22outside%22%2C%22event_type%22%3A%22hot_board%22%2C%22hot_board_cluster_id%22%3A%227651272977132109833%22%2C%22hot_board_impr_id%22%3A%2220260615202157ABC07E8618FDA919B432%22%2C%22jump_page%22%3A%22hot_board_page%22%2C%22location%22%3A%22news_hot_card%22%2C%22page_location%22%3A%22hot_board_page%22%2C%22source%22%3A%22trending_tab%22%2C%22style_id%22%3A%2240132%22%2C%22title%22%3A%223%E4%BA%BF%E5%8C%97%E6%96%97%E5%B7%A5%E7%A8%8B%E7%8E%B0%E2%80%9C%E8%84%86%E7%9A%AE%E5%BA%95%E5%BA%A7%E2%80%9D%22%7D&rank=&style_id=40132&topic_id=7651272977132109833",
          "hot": "490万",
          "platform": "toutiao"
        },
        {
          "rank": 17,
          "title": "如何看待遇见小面霸凌式维权",
          "url": "https://www.toutiao.com/trending/7651565503701323307/?category_name=topic_innerflow&event_type=hot_board&log_pb=%7B%22category_name%22%3A%22topic_innerflow%22%2C%22cluster_type%22%3A%2213%22%2C%22enter_from%22%3A%22click_category%22%2C%22entrance_hotspot%22%3A%22outside%22%2C%22event_type%22%3A%22hot_board%22%2C%22hot_board_cluster_id%22%3A%227651565503701323307%22%2C%22hot_board_impr_id%22%3A%2220260615202157ABC07E8618FDA919B432%22%2C%22jump_page%22%3A%22hot_board_page%22%2C%22location%22%3A%22news_hot_card%22%2C%22page_location%22%3A%22hot_board_page%22%2C%22source%22%3A%22trending_tab%22%2C%22style_id%22%3A%2240132%22%2C%22title%22%3A%22%E5%A6%82%E4%BD%95%E7%9C%8B%E5%BE%85%E9%81%87%E8%A7%81%E5%B0%8F%E9%9D%A2%E9%9C%B8%E5%87%8C%E5%BC%8F%E7%BB%B4%E6%9D%83%22%7D&rank=&style_id=40132&topic_id=7651565503701323307",
          "hot": "444万",
          "platform": "toutiao"
        },
        {
          "rank": 18,
          "title": "孙继海徐云龙回忆世界杯",
          "url": "https://www.toutiao.com/trending/7650505670391136310/?category_name=topic_innerflow&event_type=hot_board&log_pb=%7B%22category_name%22%3A%22topic_innerflow%22%2C%22cluster_type%22%3A%222%22%2C%22enter_from%22%3A%22click_category%22%2C%22entrance_hotspot%22%3A%22outside%22%2C%22event_type%22%3A%22hot_board%22%2C%22hot_board_cluster_id%22%3A%227650505670391136310%22%2C%22hot_board_impr_id%22%3A%2220260615202157ABC07E8618FDA919B432%22%2C%22jump_page%22%3A%22hot_board_page%22%2C%22location%22%3A%22news_hot_card%22%2C%22page_location%22%3A%22hot_board_page%22%2C%22source%22%3A%22trending_tab%22%2C%22style_id%22%3A%2240132%22%2C%22title%22%3A%22%E5%AD%99%E7%BB%A7%E6%B5%B7%E5%BE%90%E4%BA%91%E9%BE%99%E5%9B%9E%E5%BF%86%E4%B8%96%E7%95%8C%E6%9D%AF%22%7D&rank=&style_id=40132&topic_id=7650505670391136310",
          "hot": "401万",
          "platform": "toutiao"
        },
        {
          "rank": 19,
          "title": "男子家中离奇中毒岳母再婚丈夫被抓",
          "url": "https://www.toutiao.com/trending/7651511244318359571/?category_name=topic_innerflow&event_type=hot_board&log_pb=%7B%22category_name%22%3A%22topic_innerflow%22%2C%22cluster_type%22%3A%220%22%2C%22enter_from%22%3A%22click_category%22%2C%22entrance_hotspot%22%3A%22outside%22%2C%22event_type%22%3A%22hot_board%22%2C%22hot_board_cluster_id%22%3A%227651511244318359571%22%2C%22hot_board_impr_id%22%3A%2220260615202157ABC07E8618FDA919B432%22%2C%22jump_page%22%3A%22hot_board_page%22%2C%22location%22%3A%22news_hot_card%22%2C%22page_location%22%3A%22hot_board_page%22%2C%22source%22%3A%22trending_tab%22%2C%22style_id%22%3A%2240132%22%2C%22title%22%3A%22%E7%94%B7%E5%AD%90%E5%AE%B6%E4%B8%AD%E7%A6%BB%E5%A5%87%E4%B8%AD%E6%AF%92%E5%B2%B3%E6%AF%8D%E5%86%8D%E5%A9%9A%E4%B8%88%E5%A4%AB%E8%A2%AB%E6%8A%93%22%7D&rank=&style_id=40132&topic_id=7651511244318359571",
          "hot": "363万",
          "platform": "toutiao"
        },
        {
          "rank": 20,
          "title": "广东局地降大暴雨 街道内涝深至小腿",
          "url": "https://www.toutiao.com/trending/7650415646152622099/?category_name=topic_innerflow&event_type=hot_board&log_pb=%7B%22category_name%22%3A%22topic_innerflow%22%2C%22cluster_type%22%3A%229%22%2C%22enter_from%22%3A%22click_category%22%2C%22entrance_hotspot%22%3A%22outside%22%2C%22event_type%22%3A%22hot_board%22%2C%22hot_board_cluster_id%22%3A%227650415646152622099%22%2C%22hot_board_impr_id%22%3A%2220260615202157ABC07E8618FDA919B432%22%2C%22jump_page%22%3A%22hot_board_page%22%2C%22location%22%3A%22news_hot_card%22%2C%22page_location%22%3A%22hot_board_page%22%2C%22source%22%3A%22trending_tab%22%2C%22style_id%22%3A%2240132%22%2C%22title%22%3A%22%E5%B9%BF%E4%B8%9C%E5%B1%80%E5%9C%B0%E9%99%8D%E5%A4%A7%E6%9A%B4%E9%9B%A8+%E8%A1%97%E9%81%93%E5%86%85%E6%B6%9D%E6%B7%B1%E8%87%B3%E5%B0%8F%E8%85%BF%22%7D&rank=&style_id=40132&topic_id=7650415646152622099",
          "hot": "328万",
          "platform": "toutiao"
        },
        {
          "rank": 21,
          "title": "媒体评宝妈考编第一遭撤岗",
          "url": "https://www.toutiao.com/trending/7650883407911632934/?category_name=topic_innerflow&event_type=hot_board&log_pb=%7B%22category_name%22%3A%22topic_innerflow%22%2C%22cluster_type%22%3A%221%22%2C%22enter_from%22%3A%22click_category%22%2C%22entrance_hotspot%22%3A%22outside%22%2C%22event_type%22%3A%22hot_board%22%2C%22hot_board_cluster_id%22%3A%227650883407911632934%22%2C%22hot_board_impr_id%22%3A%2220260615202157ABC07E8618FDA919B432%22%2C%22jump_page%22%3A%22hot_board_page%22%2C%22location%22%3A%22news_hot_card%22%2C%22page_location%22%3A%22hot_board_page%22%2C%22source%22%3A%22trending_tab%22%2C%22style_id%22%3A%2240132%22%2C%22title%22%3A%22%E5%AA%92%E4%BD%93%E8%AF%84%E5%AE%9D%E5%A6%88%E8%80%83%E7%BC%96%E7%AC%AC%E4%B8%80%E9%81%AD%E6%92%A4%E5%B2%97%22%7D&rank=&style_id=40132&topic_id=7650883407911632934",
          "hot": "297万",
          "platform": "toutiao"
        },
        {
          "rank": 22,
          "title": "波兰地下挖出32具胎儿遗骸",
          "url": "https://www.toutiao.com/trending/7650683340731678766/?category_name=topic_innerflow&event_type=hot_board&log_pb=%7B%22category_name%22%3A%22topic_innerflow%22%2C%22cluster_type%22%3A%226%22%2C%22enter_from%22%3A%22click_category%22%2C%22entrance_hotspot%22%3A%22outside%22%2C%22event_type%22%3A%22hot_board%22%2C%22hot_board_cluster_id%22%3A%227650683340731678766%22%2C%22hot_board_impr_id%22%3A%2220260615202157ABC07E8618FDA919B432%22%2C%22jump_page%22%3A%22hot_board_page%22%2C%22location%22%3A%22news_hot_card%22%2C%22page_location%22%3A%22hot_board_page%22%2C%22source%22%3A%22trending_tab%22%2C%22style_id%22%3A%2240132%22%2C%22title%22%3A%22%E6%B3%A2%E5%85%B0%E5%9C%B0%E4%B8%8B%E6%8C%96%E5%87%BA32%E5%85%B7%E8%83%8E%E5%84%BF%E9%81%97%E9%AA%B8%22%7D&rank=&style_id=40132&topic_id=7650683340731678766",
          "hot": "269万",
          "platform": "toutiao"
        },
        {
          "rank": 23,
          "title": "李书福张雪联手将推动中国举办WSBK",
          "url": "https://www.toutiao.com/trending/7650948598826336292/?category_name=topic_innerflow&event_type=hot_board&log_pb=%7B%22category_name%22%3A%22topic_innerflow%22%2C%22cluster_type%22%3A%222%22%2C%22enter_from%22%3A%22click_category%22%2C%22entrance_hotspot%22%3A%22outside%22%2C%22event_type%22%3A%22hot_board%22%2C%22hot_board_cluster_id%22%3A%227650948598826336292%22%2C%22hot_board_impr_id%22%3A%2220260615202157ABC07E8618FDA919B432%22%2C%22jump_page%22%3A%22hot_board_page%22%2C%22location%22%3A%22news_hot_card%22%2C%22page_location%22%3A%22hot_board_page%22%2C%22source%22%3A%22trending_tab%22%2C%22style_id%22%3A%2240132%22%2C%22title%22%3A%22%E6%9D%8E%E4%B9%A6%E7%A6%8F%E5%BC%A0%E9%9B%AA%E8%81%94%E6%89%8B%E5%B0%86%E6%8E%A8%E5%8A%A8%E4%B8%AD%E5%9B%BD%E4%B8%BE%E5%8A%9EWSBK%22%7D&rank=&style_id=40132&topic_id=7650948598826336292",
          "hot": "243万",
          "platform": "toutiao"
        },
        {
          "rank": 24,
          "title": "广东惠来暴雨多人凌晨在国道抓鱼",
          "url": "https://www.toutiao.com/trending/7650648001567997998/?category_name=topic_innerflow&event_type=hot_board&log_pb=%7B%22category_name%22%3A%22topic_innerflow%22%2C%22cluster_type%22%3A%226%22%2C%22enter_from%22%3A%22click_category%22%2C%22entrance_hotspot%22%3A%22outside%22%2C%22event_type%22%3A%22hot_board%22%2C%22hot_board_cluster_id%22%3A%227650648001567997998%22%2C%22hot_board_impr_id%22%3A%2220260615202157ABC07E8618FDA919B432%22%2C%22jump_page%22%3A%22hot_board_page%22%2C%22location%22%3A%22news_hot_card%22%2C%22page_location%22%3A%22hot_board_page%22%2C%22source%22%3A%22trending_tab%22%2C%22style_id%22%3A%2240132%22%2C%22title%22%3A%22%E5%B9%BF%E4%B8%9C%E6%83%A0%E6%9D%A5%E6%9A%B4%E9%9B%A8%E5%A4%9A%E4%BA%BA%E5%87%8C%E6%99%A8%E5%9C%A8%E5%9B%BD%E9%81%93%E6%8A%93%E9%B1%BC%22%7D&rank=&style_id=40132&topic_id=7650648001567997998",
          "hot": "220万",
          "platform": "toutiao"
        },
        {
          "rank": 25,
          "title": "名嘴讽日本想与蒙古国合作开采稀土",
          "url": "https://www.toutiao.com/trending/7650180069737906186/?category_name=topic_innerflow&event_type=hot_board&log_pb=%7B%22category_name%22%3A%22topic_innerflow%22%2C%22cluster_type%22%3A%228%22%2C%22enter_from%22%3A%22click_category%22%2C%22entrance_hotspot%22%3A%22outside%22%2C%22event_type%22%3A%22hot_board%22%2C%22hot_board_cluster_id%22%3A%227650180069737906186%22%2C%22hot_board_impr_id%22%3A%2220260615202157ABC07E8618FDA919B432%22%2C%22jump_page%22%3A%22hot_board_page%22%2C%22location%22%3A%22news_hot_card%22%2C%22page_location%22%3A%22hot_board_page%22%2C%22source%22%3A%22trending_tab%22%2C%22style_id%22%3A%2240132%22%2C%22title%22%3A%22%E5%90%8D%E5%98%B4%E8%AE%BD%E6%97%A5%E6%9C%AC%E6%83%B3%E4%B8%8E%E8%92%99%E5%8F%A4%E5%9B%BD%E5%90%88%E4%BD%9C%E5%BC%80%E9%87%87%E7%A8%80%E5%9C%9F%22%7D&rank=&style_id=40132&topic_id=7650180069737906186",
          "hot": "199万",
          "platform": "toutiao"
        },
        {
          "rank": 26,
          "title": "森保一又掏出小本子做笔记",
          "url": "https://www.toutiao.com/trending/7650495256223465510/?category_name=topic_innerflow&event_type=hot_board&log_pb=%7B%22category_name%22%3A%22topic_innerflow%22%2C%22cluster_type%22%3A%221%22%2C%22enter_from%22%3A%22click_category%22%2C%22entrance_hotspot%22%3A%22outside%22%2C%22event_type%22%3A%22hot_board%22%2C%22hot_board_cluster_id%22%3A%227650495256223465510%22%2C%22hot_board_impr_id%22%3A%2220260615202157ABC07E8618FDA919B432%22%2C%22jump_page%22%3A%22hot_board_page%22%2C%22location%22%3A%22news_hot_card%22%2C%22page_location%22%3A%22hot_board_page%22%2C%22source%22%3A%22trending_tab%22%2C%22style_id%22%3A%2240132%22%2C%22title%22%3A%22%E6%A3%AE%E4%BF%9D%E4%B8%80%E5%8F%88%E6%8E%8F%E5%87%BA%E5%B0%8F%E6%9C%AC%E5%AD%90%E5%81%9A%E7%AC%94%E8%AE%B0%22%7D&rank=&style_id=40132&topic_id=7650495256223465510",
          "hot": "180万",
          "platform": "toutiao"
        },
        {
          "rank": 27,
          "title": "加前总理称看美国比赛是尽男友本分",
          "url": "https://www.toutiao.com/trending/7651322897906729001/?category_name=topic_innerflow&event_type=hot_board&log_pb=%7B%22category_name%22%3A%22topic_innerflow%22%2C%22cluster_type%22%3A%222%22%2C%22enter_from%22%3A%22click_category%22%2C%22entrance_hotspot%22%3A%22outside%22%2C%22event_type%22%3A%22hot_board%22%2C%22hot_board_cluster_id%22%3A%227651322897906729001%22%2C%22hot_board_impr_id%22%3A%2220260615202157ABC07E8618FDA919B432%22%2C%22jump_page%22%3A%22hot_board_page%22%2C%22location%22%3A%22news_hot_card%22%2C%22page_location%22%3A%22hot_board_page%22%2C%22source%22%3A%22trending_tab%22%2C%22style_id%22%3A%2240132%22%2C%22title%22%3A%22%E5%8A%A0%E5%89%8D%E6%80%BB%E7%90%86%E7%A7%B0%E7%9C%8B%E7%BE%8E%E5%9B%BD%E6%AF%94%E8%B5%9B%E6%98%AF%E5%B0%BD%E7%94%B7%E5%8F%8B%E6%9C%AC%E5%88%86%22%7D&rank=&style_id=40132&topic_id=7651322897906729001",
          "hot": "163万",
          "platform": "toutiao"
        },
        {
          "rank": 28,
          "title": "道州龙船赛女子队和男子队同台竞技",
          "url": "https://www.toutiao.com/trending/7650851524992483347/?category_name=topic_innerflow&event_type=hot_board&log_pb=%7B%22category_name%22%3A%22topic_innerflow%22%2C%22cluster_type%22%3A%226%22%2C%22enter_from%22%3A%22click_category%22%2C%22entrance_hotspot%22%3A%22outside%22%2C%22event_type%22%3A%22hot_board%22%2C%22hot_board_cluster_id%22%3A%227650851524992483347%22%2C%22hot_board_impr_id%22%3A%2220260615202157ABC07E8618FDA919B432%22%2C%22jump_page%22%3A%22hot_board_page%22%2C%22location%22%3A%22news_hot_card%22%2C%22page_location%22%3A%22hot_board_page%22%2C%22source%22%3A%22trending_tab%22%2C%22style_id%22%3A%2240132%22%2C%22title%22%3A%22%E9%81%93%E5%B7%9E%E9%BE%99%E8%88%B9%E8%B5%9B%E5%A5%B3%E5%AD%90%E9%98%9F%E5%92%8C%E7%94%B7%E5%AD%90%E9%98%9F%E5%90%8C%E5%8F%B0%E7%AB%9E%E6%8A%80%22%7D&rank=&style_id=40132&topic_id=7650851524992483347",
          "hot": "147万",
          "platform": "toutiao"
        },
        {
          "rank": 29,
          "title": "官方通报“21车冻货跨省偏航被查扣”",
          "url": "https://www.toutiao.com/trending/7651090362706054698/?category_name=topic_innerflow&event_type=hot_board&log_pb=%7B%22category_name%22%3A%22topic_innerflow%22%2C%22cluster_type%22%3A%222%22%2C%22enter_from%22%3A%22click_category%22%2C%22entrance_hotspot%22%3A%22outside%22%2C%22event_type%22%3A%22hot_board%22%2C%22hot_board_cluster_id%22%3A%227651090362706054698%22%2C%22hot_board_impr_id%22%3A%2220260615202157ABC07E8618FDA919B432%22%2C%22jump_page%22%3A%22hot_board_page%22%2C%22location%22%3A%22news_hot_card%22%2C%22page_location%22%3A%22hot_board_page%22%2C%22source%22%3A%22trending_tab%22%2C%22style_id%22%3A%2240132%22%2C%22title%22%3A%22%E5%AE%98%E6%96%B9%E9%80%9A%E6%8A%A5%E2%80%9C21%E8%BD%A6%E5%86%BB%E8%B4%A7%E8%B7%A8%E7%9C%81%E5%81%8F%E8%88%AA%E8%A2%AB%E6%9F%A5%E6%89%A3%E2%80%9D%22%7D&rank=&style_id=40132&topic_id=7651090362706054698",
          "hot": "133万",
          "platform": "toutiao"
        },
        {
          "rank": 30,
          "title": "台媒：两岸舆论相向而行是好事",
          "url": "https://www.toutiao.com/trending/7651080169986064403/?category_name=topic_innerflow&event_type=hot_board&log_pb=%7B%22category_name%22%3A%22topic_innerflow%22%2C%22cluster_type%22%3A%226%22%2C%22enter_from%22%3A%22click_category%22%2C%22entrance_hotspot%22%3A%22outside%22%2C%22event_type%22%3A%22hot_board%22%2C%22hot_board_cluster_id%22%3A%227651080169986064403%22%2C%22hot_board_impr_id%22%3A%2220260615202157ABC07E8618FDA919B432%22%2C%22jump_page%22%3A%22hot_board_page%22%2C%22location%22%3A%22news_hot_card%22%2C%22page_location%22%3A%22hot_board_page%22%2C%22source%22%3A%22trending_tab%22%2C%22style_id%22%3A%2240132%22%2C%22title%22%3A%22%E5%8F%B0%E5%AA%92%EF%BC%9A%E4%B8%A4%E5%B2%B8%E8%88%86%E8%AE%BA%E7%9B%B8%E5%90%91%E8%80%8C%E8%A1%8C%E6%98%AF%E5%A5%BD%E4%BA%8B%22%7D&rank=&style_id=40132&topic_id=7651080169986064403",
          "hot": "121万",
          "platform": "toutiao"
        }
      ]
    }
  }
}